jiragap/__init__.py
jiragap-0.1.2.dist-info/DESCRIPTION.rst
jiragap-0.1.2.dist-info/METADATA
jiragap-0.1.2.dist-info/RECORD
jiragap-0.1.2.dist-info/WHEEL
jiragap-0.1.2.dist-info/metadata.json
jiragap-0.1.2.dist-info/top_level.txt
