Metadata-Version: 2.0
Name: jiragap
Version: 0.1.2
Summary: A contract package for interacting with an instance of Atlassian Jira
Home-page: https://github.com/FoleyDiver/jiragap
Author: Steve Foley
Author-email: sfoley1988@gmail.com
License: GPLv2+
Download-URL: https://github.com/FoleyDiver/jiragap/archive/v0.1.2.tar.gz
Platform: UNKNOWN
Classifier: Development Status :: 3 - Alpha
Classifier: License :: OSI Approved :: GNU General Public License v2 or later (GPLv2+)
Classifier: Intended Audience :: Developers
Classifier: Programming Language :: Python :: 3.4
Classifier: Programming Language :: Python :: 3.5
Classifier: Programming Language :: Python :: 3.6
